kcuda_validate/__init__.py
kcuda_validate/__main__.py
kcuda_validate/cli/__init__.py
kcuda_validate/cli/detect.py
kcuda_validate/cli/infer.py
kcuda_validate/cli/load.py
kcuda_validate/cli/validate_all.py
kcuda_validate/lib/__init__.py
kcuda_validate/lib/formatters.py
kcuda_validate/lib/logger.py
kcuda_validate/lib/metrics.py
kcuda_validate/lib/validators.py
kcuda_validate/models/__init__.py
kcuda_validate/models/gpu_device.py
kcuda_validate/models/inference_result.py
kcuda_validate/models/llm_model.py
kcuda_validate/services/__init__.py
kcuda_validate/services/gpu_detector.py
kcuda_validate/services/inferencer.py
kcuda_validate/services/model_loader.py
kcuda_validate-0.1.2.dist-info/METADATA
kcuda_validate-0.1.2.dist-info/WHEEL
kcuda_validate-0.1.2.dist-info/entry_points.txt
kcuda_validate-0.1.2.dist-info/RECORD
