Metadata-Version: 2.4
Name: kcuda-validate
Version: 0.1.2
Summary: CUDA LLM Hardware Validation Tool for WSL2
Project-URL: Homepage, https://github.com/kenhia/kcuda
Project-URL: Documentation, https://github.com/kenhia/kcuda/blob/main/specs/001-cuda-llm-validation/quickstart.md
Project-URL: Repository, https://github.com/kenhia/kcuda
Project-URL: Bug Tracker, https://github.com/kenhia/kcuda/issues
Project-URL: Changelog, https://github.com/kenhia/kcuda/releases
Author-email: Ken Hiatt <ken.hiatt@gmail.com>
License: MIT
Keywords: cuda,gguf,gpu,inference,llm,nvidia,validation,wsl2
Classifier: Development Status :: 3 - Alpha
Classifier: Intended Audience :: Developers
Classifier: Intended Audience :: Science/Research
Classifier: License :: OSI Approved :: MIT License
Classifier: Operating System :: POSIX :: Linux
Classifier: Programming Language :: Python :: 3
Classifier: Programming Language :: Python :: 3.11
Classifier: Programming Language :: Python :: 3.12
Classifier: Topic :: Scientific/Engineering :: Artificial Intelligence
Classifier: Topic :: System :: Hardware
Requires-Python: >=3.11
Requires-Dist: click>=8.1.0
Requires-Dist: huggingface-hub>=0.19.0
Requires-Dist: llama-cpp-python>=0.2.0
Requires-Dist: nvidia-ml-py>=12.535.0
Requires-Dist: rich>=13.0.0
Requires-Dist: torch>=2.1.0
Provides-Extra: dev
Requires-Dist: pytest-cov>=7.0.0; extra == 'dev'
Requires-Dist: pytest-mock>=3.15.1; extra == 'dev'
Requires-Dist: pytest>=9.0.2; extra == 'dev'
Requires-Dist: ruff>=0.14.14; extra == 'dev'
